wasender/__init__.py
wasender/sender.py
wasender-1.0.0.dist-info/licenses/LICENSE
wasender-1.0.0.dist-info/METADATA
wasender-1.0.0.dist-info/WHEEL
wasender-1.0.0.dist-info/top_level.txt
wasender-1.0.0.dist-info/RECORD
